diacriticize/__init__.py
diacriticize/diacriticize.py
diacriticize-1.0.0.dist-info/METADATA
diacriticize-1.0.0.dist-info/WHEEL
diacriticize-1.0.0.dist-info/licenses/LICENSE
diacriticize-1.0.0.dist-info/RECORD
