Metadata-Version: 2.3
Name: diacriticize
Version: 1.0.0
Summary: A package that ḑ͌̓͜ ̧ͤ́ͫe̹͚͛̔ ̸̞̓ͩm͚̜̅́ ̷͉̽͊o̗͚̊̕ ͖̈ͧ̓l̴̢͈̋ ̲̰̅͏i̧̨̳͇ ̮̦̠͟s̢͒̎͌ ͉ͣͩ͢ḩ͙͍͌ ̵̤̿ͣe̡͑͊͊ ̯̪͙̅s̶ͬ͒̆ strings
Project-URL: Homepage, https://github.com/donotsolveme/diacriticize
Project-URL: Issues, https://github.com/donotsolveme/diacriticize/issues
Author: qono konoha
License-File: LICENSE
Classifier: License :: OSI Approved :: MIT License
Classifier: Programming Language :: Python :: 3
Requires-Python: >=3.8
